coder_retriever/__init__.py
coder_retriever/ai/__init__.py
coder_retriever/ai/assistant.py
coder_retriever-0.1.4.dist-info/LICENSE
coder_retriever-0.1.4.dist-info/METADATA
coder_retriever-0.1.4.dist-info/WHEEL
coder_retriever-0.1.4.dist-info/RECORD
