Metadata-Version: 2.1
Name: coder-retriever
Version: 0.1.4
Summary: Coder Retriever: your loyal coding companion
License: MIT
Author: GitMarco27
Author-email: 72693100+GitMarco27@users.noreply.github.com
Requires-Python: >=3.9,<4.0
Classifier: License :: OSI Approved :: MIT License
Classifier: Programming Language :: Python :: 3
Classifier: Programming Language :: Python :: 3.9
Classifier: Programming Language :: Python :: 3.10
Classifier: Programming Language :: Python :: 3.11
Requires-Dist: black (>=23.7.0,<24.0.0)
Requires-Dist: flake8 (>=6.1.0,<7.0.0)
Requires-Dist: ipykernel (>=6.24.0,<7.0.0)
Requires-Dist: isort (>=5.12.0,<6.0.0)
Requires-Dist: matplotlib (>=3.7.2,<4.0.0)
Requires-Dist: mypy (>=1.5.1,<2.0.0)
Requires-Dist: no-implicit-optional (>=1.4,<2.0)
Requires-Dist: numpy (>=1.23,<2.0)
Requires-Dist: openai (>=0.27.8,<0.28.0)
Requires-Dist: pandas (>=1.5.3,<2.0.0)
Requires-Dist: python-dotenv (>=1.0.0,<2.0.0)
